[
    {
      "id": 1,
      "picImg": "https://res.vmallres.com/pimages//product/6901443223473/428_428_1542936556453mp.png",
      "title": "华为手环B3 青春版",
      "price":"4988",
      "hot":"853",
      "time":"2016-04-11"
    },
    {
      "id": 2,
      "picImg": "https://res.vmallres.com/pimages//product/6901443203956/428_428_1542854771585mp.png",
      "title": "华为手环B3 青春版",
      "price":"88",
      "hot":"635",
      "time":"2017-10-11"
    },
    {
      "id": 3,
      "picImg": "https://res.vmallres.com/pimages//product/6901443223473/428_428_1542936556453mp.png",
      "title": "华为手环B3 青春版",
      "price":"2988",
      "hot":"753",
      "time":"2016-09-06"
    },
    {
      "id": 4,
      "picImg": "https://res.vmallres.com/pimages//product/6901443203956/428_428_1542854771585mp.png",
      "title": "华为手环B3 青春版",
      "price":"5988",
      "hot":"53",
      "time":"2018-05-23"
    },
    {
      "id": 5,
      "picImg": "https://res.vmallres.com/pimages//product/6901443223473/428_428_1542936556453mp.png",
      "title": "华为手环B3 青春版",
      "price":"388",
      "hot":"153",
      "time":"2012-07-18"
    }
  ]